{"is_sample_playing":true,"download_path":"http:\/\/api.ritmo.media\/api\/tracks\/10554\/download","free_to":0,"name_fa":"\u062a\u0635\u0646\u06cc\u0641 \u062f\u0648\u0644\u062a \u0639\u0634\u0642","like_count":0,"lyric":"","thumbnail_list":{"x_200":{"image_path_absolute":"http:\/\/api.ritmo.media\/media\/cache\/2b\/ea\/2bea77b0fa20632d3301431449c7bbd4.jpg","size":[200,200]},"x_500":{"image_path_absolute":"http:\/\/api.ritmo.media\/media\/cache\/50\/b9\/50b9a1daf95641b37b74b2027866b9e1.jpg","size":[500,500]}},"id":10554,"file_duration_formatted":"1':25''","rtmp_path":"mp4:ritmo\/128\/sample_44100_2_d1419302db9c022ab1d48681b13d5f8b.m4a","free_to_download":false,"dislike_count":0,"file_size_MB":16.27,"rtmp_base":"rtmp:\/\/ritmo.ir:8080\/saod","album_info":{"album_name":"\u06af\u0644\u0628\u0627\u0646\u06af \u0634\u062c\u0631\u06cc\u0627\u0646 (\u062f\u0648\u0644\u062a \u0639\u0634\u0642)","album_id":895},"publish_time":{"year":null,"month":null},"rbt_code":"","description":"","rtsp_path":"rtsp:\/\/ritmo.ir:8080\/saod\/_definst_\/mp4:ritmo\/128\/sample_44100_2_d1419302db9c022ab1d48681b13d5f8b.m4a","hls_path":"http:\/\/ritmo.ir:8080\/saod\/_definst_\/mp4:ritmo\/128\/sample_44100_2_d1419302db9c022ab1d48681b13d5f8b.m4a\/playlist.m3u8","file_duration":85,"price":1000.0,"free_from":0,"file_checksum":"91c7a712775749939341ab0f2db5646d","name_en":"Dashti - Tasnif-E Dowlat-E Eshq","image_path_absolute":"http:\/\/api.ritmo.media\/media\/album\/images\/20aee3a5f4643755a79ee5f6a73050ac.jpg","file_duration_real":426,"track_number":8,"artists_info":[{"name_fa":"\u0645\u062d\u0645\u062f\u0631\u0636\u0627 \u0634\u062c\u0631\u06cc\u0627\u0646","name_en":"Mohammadreza Shajarian","type":"singer","id":503}],"free_to_listen":false,"user_activity":null}