{"is_sample_playing":true,"download_path":"http:\/\/api.ritmo.media\/api\/tracks\/10915\/download","free_to":0,"name_fa":"Sea Monster","like_count":0,"lyric":"","thumbnail_list":{"x_200":{"image_path_absolute":"http:\/\/api.ritmo.media\/media\/cache\/fd\/33\/fd33d02c3cf7e2760e3e15b26f44fb1c.jpg","size":[200,197]},"x_500":{"image_path_absolute":"http:\/\/api.ritmo.media\/media\/cache\/50\/53\/50533dee6324577103087a89f5ca392f.jpg","size":[500,493]}},"id":10915,"file_duration_formatted":"1':38''","rtmp_path":"mp4:ritmo\/128\/sample_44100_2_28141c5d643609aa9279d7647d706018.m4a","free_to_download":false,"dislike_count":0,"file_size_MB":18.84,"rtmp_base":"rtmp:\/\/ritmo.ir:8080\/saod","album_info":{"album_name":"\u0628\u0627\u0631\u0627\u0646 \u0622\u0641\u062a\u0627\u0628\u06cc","album_id":918},"publish_time":{"year":null,"month":null},"rbt_code":"","description":"","rtsp_path":"rtsp:\/\/ritmo.ir:8080\/saod\/_definst_\/mp4:ritmo\/128\/sample_44100_2_28141c5d643609aa9279d7647d706018.m4a","hls_path":"http:\/\/ritmo.ir:8080\/saod\/_definst_\/mp4:ritmo\/128\/sample_44100_2_28141c5d643609aa9279d7647d706018.m4a\/playlist.m3u8","file_duration":98,"price":400.0,"free_from":0,"file_checksum":"737d45f798c4fd3ee2e1e6a72a35d979","name_en":"Track 5","image_path_absolute":"http:\/\/api.ritmo.media\/media\/album\/images\/1e056d2b0ebd5c878c550da6ac5d3724.jpg","file_duration_real":493,"track_number":5,"artists_info":[{"name_fa":"\u0639\u0632\u06cc\u0632\u0627 \u0645\u0635\u0637\u0641\u06cc \u0632\u0627\u062f\u0647","name_en":"Aziza Mostafa Zade","type":"musician","id":652}],"free_to_listen":false,"user_activity":null}