{"is_sample_playing":true,"download_path":"http:\/\/api.ritmo.media\/api\/tracks\/3146\/download","free_to":0,"name_fa":"","like_count":0,"lyric":"","thumbnail_list":{},"id":3146,"file_duration_formatted":"45''","rtmp_path":"mp4:ritmo\/128\/sample_44100_2_5d4ae76f053f8f2516ad12961ef7fe97.m4a","free_to_download":false,"dislike_count":0,"file_size_MB":8.7,"rtmp_base":"rtmp:\/\/ritmo.ir:8080\/saod","album_info":{"album_name":"\u0631\u0648\u06cc\u0627\u0647\u0627\u06cc \u06a9\u0644\u0627\u0633\u06cc\u06a9","album_id":223},"publish_time":{"year":null,"month":null},"rbt_code":"","description":"","rtsp_path":"rtsp:\/\/ritmo.ir:8080\/saod\/_definst_\/mp4:ritmo\/128\/sample_44100_2_5d4ae76f053f8f2516ad12961ef7fe97.m4a","hls_path":"http:\/\/ritmo.ir:8080\/saod\/_definst_\/mp4:ritmo\/128\/sample_44100_2_5d4ae76f053f8f2516ad12961ef7fe97.m4a\/playlist.m3u8","file_duration":45,"price":200.0,"free_from":0,"file_checksum":"e03ea6e4babf7ab2f2b89d9c4f86e498","name_en":"I Just Called to Say I Love You","image_path_absolute":null,"file_duration_real":228,"track_number":2,"artists_info":[{"name_fa":"\u0641\u0631\u0627\u0646\u0633\u06cc\u0633 \u06af\u0648\u06cc\u0627","name_en":"francis goya","type":"singer","id":233}],"free_to_listen":false,"user_activity":null}