{"is_sample_playing":true,"download_path":"http:\/\/api.ritmo.media\/api\/tracks\/4827\/download","free_to":0,"name_fa":"\u0627\u0634\u06a9 \u062a\u0646\u0647\u0627\u06cc\u06cc 1","like_count":0,"lyric":"","thumbnail_list":{"x_200":{"image_path_absolute":"http:\/\/api.ritmo.media\/media\/cache\/00\/71\/00719a05c7ee8c5a493f3ae6446d8ecb.jpg","size":[200,242]},"x_500":{"image_path_absolute":"http:\/\/api.ritmo.media\/media\/cache\/e4\/4d\/e44d9c376ee98aa939a5b8918ab2ac5d.jpg","size":[500,605]}},"id":4827,"file_duration_formatted":"5':53''","rtmp_path":"mp4:ritmo\/128\/sample_44100_2_5857d68cd9280bc98d079fa912fd6740.m4a","free_to_download":false,"dislike_count":0,"file_size_MB":67.48,"rtmp_base":"rtmp:\/\/ritmo.ir:8080\/saod","album_info":{"album_name":"\u0627\u0634\u06a9 \u062a\u0646\u0647\u0627\u06cc\u06cc","album_id":394},"publish_time":{"year":null,"month":null},"rbt_code":"","description":"","rtsp_path":"rtsp:\/\/ritmo.ir:8080\/saod\/_definst_\/mp4:ritmo\/128\/sample_44100_2_5857d68cd9280bc98d079fa912fd6740.m4a","hls_path":"http:\/\/ritmo.ir:8080\/saod\/_definst_\/mp4:ritmo\/128\/sample_44100_2_5857d68cd9280bc98d079fa912fd6740.m4a\/playlist.m3u8","file_duration":353,"price":500.0,"free_from":0,"file_checksum":"356aac4bb9d1f518d18ee5f39b49bb37","name_en":"ashke tanhayi 1","image_path_absolute":"http:\/\/api.ritmo.media\/media\/album\/images\/28f0b864598a1291557bed248a998d4e.jpg","file_duration_real":1769,"track_number":1,"artists_info":[{"name_fa":"\u0645\u0646\u0635\u0648\u0631 \u062d\u0633\u0646 \u067e\u0648\u0631","name_en":"mansoor hasan por","type":"singer","id":336}],"free_to_listen":false,"user_activity":null}