{"is_sample_playing":true,"download_path":"http:\/\/api.ritmo.media\/api\/tracks\/5390\/download","free_to":0,"name_fa":" \u0622\u0631\u0632\u0648 \u0647\u0627 2","like_count":0,"lyric":"","thumbnail_list":{"x_200":{"image_path_absolute":"http:\/\/api.ritmo.media\/media\/cache\/2e\/0d\/2e0d743b16881651030296e8c595118c.jpg","size":[200,200]},"x_500":{"image_path_absolute":"http:\/\/api.ritmo.media\/media\/cache\/f0\/69\/f069302810d7e1f45ab8dc1e15895bea.jpg","size":[500,500]}},"id":5390,"file_duration_formatted":"49''","rtmp_path":"mp4:ritmo\/128\/sample_44100_2_4e5046fc8d6a97d18a5f54beaed54dea.m4a","free_to_download":false,"dislike_count":0,"file_size_MB":5.72,"rtmp_base":"rtmp:\/\/ritmo.ir:8080\/saod","album_info":{"album_name":"\u0632\u06cc \u0628\u0627\u0632\u06cc","album_id":453},"publish_time":{"year":null,"month":null},"rbt_code":"","description":"","rtsp_path":"rtsp:\/\/ritmo.ir:8080\/saod\/_definst_\/mp4:ritmo\/128\/sample_44100_2_4e5046fc8d6a97d18a5f54beaed54dea.m4a","hls_path":"http:\/\/ritmo.ir:8080\/saod\/_definst_\/mp4:ritmo\/128\/sample_44100_2_4e5046fc8d6a97d18a5f54beaed54dea.m4a\/playlist.m3u8","file_duration":49,"price":1100.0,"free_from":0,"file_checksum":"3e1e23ce92d57a371ae32a518c0610a3","name_en":"arezooha 2","image_path_absolute":"http:\/\/api.ritmo.media\/media\/album\/images\/49ae49a23f67c759bf4fc791ba842aa2.jpg","file_duration_real":249,"track_number":3,"artists_info":[{"name_fa":"\u0631\u0627\u0645\u06cc\u0646 \u0628\u0647\u0646\u0627","name_en":"ramin bahna","type":"singer","id":369},{"name_fa":"\u0647\u0648\u0645\u0646 \u062c\u0627\u0648\u06cc\u062f","name_en":"hooman javid","type":"singer","id":387}],"free_to_listen":false,"user_activity":null}