{"is_sample_playing":true,"download_path":"http:\/\/api.ritmo.media\/api\/tracks\/5638\/download","free_to":0,"name_fa":" El Testament d'Amelia","like_count":0,"lyric":"","thumbnail_list":{"x_200":{"image_path_absolute":"http:\/\/api.ritmo.media\/media\/cache\/56\/1c\/561ca73b8cd50a09f0564f7fa351f2aa.jpg","size":[200,200]},"x_500":{"image_path_absolute":"http:\/\/api.ritmo.media\/media\/cache\/8d\/6c\/8d6c0e981971e01a89adaf4443d676ee.jpg","size":[500,500]}},"id":5638,"file_duration_formatted":"36''","rtmp_path":"mp4:ritmo\/128\/sample_44100_2_78b91366b15c399bd05530e96d28a530.m4a","free_to_download":false,"dislike_count":0,"file_size_MB":3.94,"rtmp_base":"rtmp:\/\/ritmo.ir:8080\/saod","album_info":{"album_name":"\u0628\u0627\u0631\u0648\u06a9 \u062a\u0627 \u0645\u062f\u0631\u0646","album_id":472},"publish_time":{"year":null,"month":null},"rbt_code":"","description":"","rtsp_path":"rtsp:\/\/ritmo.ir:8080\/saod\/_definst_\/mp4:ritmo\/128\/sample_44100_2_78b91366b15c399bd05530e96d28a530.m4a","hls_path":"http:\/\/ritmo.ir:8080\/saod\/_definst_\/mp4:ritmo\/128\/sample_44100_2_78b91366b15c399bd05530e96d28a530.m4a\/playlist.m3u8","file_duration":36,"price":600.0,"free_from":0,"file_checksum":"59fd2f612c178855c977a8c362be1f1a","name_en":" El Testament d'Amelia","image_path_absolute":"http:\/\/api.ritmo.media\/media\/album\/images\/ef575e8837d065a1683c022d2077d342.jpg","file_duration_real":183,"track_number":4,"artists_info":[{"name_fa":"\u0645\u062d\u0645\u062f \u0644\u0627\u0645\u0639\u06cc","name_en":"mohammad lameei","type":"singer","id":405}],"free_to_listen":false,"user_activity":null}