{"is_sample_playing":true,"download_path":"http:\/\/api.ritmo.media\/api\/tracks\/6568\/download","free_to":0,"name_fa":" \u0633\u0627\u0632 \u0648 \u0622\u0648\u0627\u0632\/\u062f\u0644\u06a9\u0634\u060c\u0642\u0631\u0686\u0647\u060c\u0631\u0636\u0648\u06cc\u060c\u0641\u0631\u0648\u062f","like_count":0,"lyric":"","thumbnail_list":{"x_200":{"image_path_absolute":"http:\/\/api.ritmo.media\/media\/cache\/67\/3a\/673a70c1f6c7a3bce821f7870881625f.jpg","size":[200,197]},"x_500":{"image_path_absolute":"http:\/\/api.ritmo.media\/media\/cache\/2b\/48\/2b48a77a4ea86bad7b1fac4ead66bd6e.jpg","size":[500,493]}},"id":6568,"file_duration_formatted":"1':43''","rtmp_path":"mp4:ritmo\/128\/sample_44100_2_1b89a2e980724cb8997459fadb907712.m4a","free_to_download":false,"dislike_count":0,"file_size_MB":19.67,"rtmp_base":"rtmp:\/\/ritmo.ir:8080\/saod","album_info":{"album_name":"\u0628\u0648\u06cc \u0645\u0647\u0631","album_id":556},"publish_time":{"year":null,"month":null},"rbt_code":"","description":"","rtsp_path":"rtsp:\/\/ritmo.ir:8080\/saod\/_definst_\/mp4:ritmo\/128\/sample_44100_2_1b89a2e980724cb8997459fadb907712.m4a","hls_path":"http:\/\/ritmo.ir:8080\/saod\/_definst_\/mp4:ritmo\/128\/sample_44100_2_1b89a2e980724cb8997459fadb907712.m4a\/playlist.m3u8","file_duration":103,"price":300.0,"free_from":0,"file_checksum":"18022e2e6b9846004ba1b9cf74d83ef3","name_en":"sazo avaz","image_path_absolute":"http:\/\/api.ritmo.media\/media\/album\/images\/11b921ef080f7736089c757404650e40.jpg","file_duration_real":515,"track_number":5,"artists_info":[{"name_fa":"\u0633\u06cc\u0646\u0627 \u0633\u0631\u0644\u06a9","name_en":"Sina Sarlak","type":"singer","id":42}],"free_to_listen":false,"user_activity":null}