{"is_sample_playing":true,"download_path":"http:\/\/api.ritmo.media\/api\/tracks\/6798\/download","free_to":0,"name_fa":" \u0622\u0648\u0627\u0632 \u0627\u0628\u0648\u0639\u0637\u0627 1","like_count":0,"lyric":"","thumbnail_list":{"x_200":{"image_path_absolute":"http:\/\/api.ritmo.media\/media\/cache\/f2\/21\/f221666d0cda3d4551ab532a24d037d4.jpg","size":[200,171]},"x_500":{"image_path_absolute":"http:\/\/api.ritmo.media\/media\/cache\/c5\/1e\/c51ebc04a6508b5fc9ef49df27866fda.jpg","size":[500,427]}},"id":6798,"file_duration_formatted":"38''","rtmp_path":"mp4:ritmo\/128\/sample_44100_2_3f78fa1cdb0e2fda88c2a935950ffdf1.m4a","free_to_download":false,"dislike_count":0,"file_size_MB":4.15,"rtmp_base":"rtmp:\/\/ritmo.ir:8080\/saod","album_info":{"album_name":"\u062a\u06a9\u0646\u0648\u0627\u0632\u06cc \u062a\u0627\u0631 \u062e\u0627\u06a9\u0633\u062a\u0631\u06cc \u060c \u0622\u0628\u06cc 1","album_id":582},"publish_time":{"year":null,"month":null},"rbt_code":"","description":"","rtsp_path":"rtsp:\/\/ritmo.ir:8080\/saod\/_definst_\/mp4:ritmo\/128\/sample_44100_2_3f78fa1cdb0e2fda88c2a935950ffdf1.m4a","hls_path":"http:\/\/ritmo.ir:8080\/saod\/_definst_\/mp4:ritmo\/128\/sample_44100_2_3f78fa1cdb0e2fda88c2a935950ffdf1.m4a\/playlist.m3u8","file_duration":38,"price":200.0,"free_from":0,"file_checksum":"2a6c3a013a8a2c5764e106447851d120","name_en":"avaze abo'ata 1","image_path_absolute":"http:\/\/api.ritmo.media\/media\/album\/images\/46922a0880a8f11f8f69cbb52b1396be.jpg","file_duration_real":193,"track_number":9,"artists_info":[{"name_fa":"\u0645\u062d\u0633\u0646 \u0646\u0641\u0631","name_en":"mohsen nafar","type":"singer","id":496}],"free_to_listen":false,"user_activity":null}