{"is_sample_playing":true,"download_path":"http:\/\/api.ritmo.media\/api\/tracks\/7717\/download","free_to":0,"name_fa":"Gloria, for 3 solo voices, chorus, trumpet, oboe, violin (ad lib), 2 violas, 2 cellos, strings & continuo in D major, RV 589: Domine ","like_count":0,"lyric":"","thumbnail_list":{"x_200":{"image_path_absolute":"http:\/\/api.ritmo.media\/media\/cache\/82\/9a\/829a8b2196558b919e7138b1e7d853cd.jpg","size":[200,200]},"x_500":{"image_path_absolute":"http:\/\/api.ritmo.media\/media\/cache\/47\/be\/47beb54db3a31cba0d5c92e32c7ac0ca.jpg","size":[500,500]}},"id":7717,"file_duration_formatted":"30''","rtmp_path":"mp4:ritmo\/128\/sample_44100_2_0d22da4bd124d386f5546323c45bc924.m4a","free_to_download":false,"dislike_count":0,"file_size_MB":5.82,"rtmp_base":"rtmp:\/\/ritmo.ir:8080\/saod","album_info":{"album_name":"\u06af\u0644\u0648\u0631\u06cc\u06271","album_id":659},"publish_time":{"year":null,"month":null},"rbt_code":"","description":"","rtsp_path":"rtsp:\/\/ritmo.ir:8080\/saod\/_definst_\/mp4:ritmo\/128\/sample_44100_2_0d22da4bd124d386f5546323c45bc924.m4a","hls_path":"http:\/\/ritmo.ir:8080\/saod\/_definst_\/mp4:ritmo\/128\/sample_44100_2_0d22da4bd124d386f5546323c45bc924.m4a\/playlist.m3u8","file_duration":30,"price":400.0,"free_from":0,"file_checksum":"a68aeda1171b29cb4f4df3ef72d5482e","name_en":"Gloria, for 3 solo voices, chorus, trumpet, oboe, violin (ad lib), 2 violas, 2 cellos, strings & continuo in D major, RV 589: Domine ","image_path_absolute":"http:\/\/api.ritmo.media\/media\/album\/images\/0ff8033cf9437c213ee13937b1c4c455.jpg","file_duration_real":152,"track_number":18,"artists_info":[{"name_fa":"\u0622\u0646\u062a\u0648\u0646\u06cc\u0648 \u0648\u06cc\u0648\u0627\u0644\u062f\u06cc","name_en":"Antonio Vivaldi","type":"singer","id":527}],"free_to_listen":false,"user_activity":null}