{"is_sample_playing":true,"download_path":"http:\/\/api.ritmo.media\/api\/tracks\/7875\/download","free_to":0,"name_fa":"\u062a\u0635\u0646\u06cc\u0641 \u062f\u0631\u062e\u062a","like_count":0,"lyric":"","thumbnail_list":{"x_200":{"image_path_absolute":"http:\/\/api.ritmo.media\/media\/cache\/fb\/24\/fb241f78188cdb9bda2c65557341da20.jpg","size":[200,180]},"x_500":{"image_path_absolute":"http:\/\/api.ritmo.media\/media\/cache\/81\/d0\/81d011f99d862457d9618f65f91f0fe7.jpg","size":[500,450]}},"id":7875,"file_duration_formatted":"1':7''","rtmp_path":"mp4:ritmo\/128\/sample_44100_2_eba237eccc24353ccaa4d62013556ac6.m4a","free_to_download":false,"dislike_count":0,"file_size_MB":12.87,"rtmp_base":"rtmp:\/\/ritmo.ir:8080\/saod","album_info":{"album_name":"\u0622\u062f\u0645 \u0648 \u0633\u0646\u06af","album_id":677},"publish_time":{"year":null,"month":null},"rbt_code":"","description":"","rtsp_path":"rtsp:\/\/ritmo.ir:8080\/saod\/_definst_\/mp4:ritmo\/128\/sample_44100_2_eba237eccc24353ccaa4d62013556ac6.m4a","hls_path":"http:\/\/ritmo.ir:8080\/saod\/_definst_\/mp4:ritmo\/128\/sample_44100_2_eba237eccc24353ccaa4d62013556ac6.m4a\/playlist.m3u8","file_duration":67,"price":800.0,"free_from":0,"file_checksum":"6d5858dd26c535fbb1d3921606b876b7","name_en":"Tansif Derakht","image_path_absolute":"http:\/\/api.ritmo.media\/media\/album\/images\/71a3cb155f8dc89bf3d0365288219936.jpg","file_duration_real":337,"track_number":5,"artists_info":[{"name_fa":"\u0645\u062c\u06cc\u062f \u062f\u0631\u062e\u0634\u0627\u0646\u06cc","name_en":"majid derakhshani","type":"singer","id":194},{"name_fa":"\u062f\u0627\u0631\u06cc\u0648\u0634 \u06a9\u0627\u0638\u0645\u06cc","name_en":"Darush Kazemi","type":"singer","id":552}],"free_to_listen":false,"user_activity":null}