{"is_sample_playing":true,"download_path":"http:\/\/api.ritmo.media\/api\/tracks\/8795\/download","free_to":0,"name_fa":"Veronique","like_count":0,"lyric":"","thumbnail_list":{"x_200":{"image_path_absolute":"http:\/\/api.ritmo.media\/media\/cache\/74\/c3\/74c30f6853fb84b02ccc7797138eb1d8.jpg","size":[200,200]},"x_500":{"image_path_absolute":"http:\/\/api.ritmo.media\/media\/cache\/9b\/20\/9b20030b246c33b6151f33ad0e541a12.jpg","size":[500,500]}},"id":8795,"file_duration_formatted":"6''","rtmp_path":"mp4:ritmo\/128\/sample_44100_2_6acb084470c0a8bdf431d5427d1f29bc.m4a","free_to_download":false,"dislike_count":0,"file_size_MB":1.32,"rtmp_base":"rtmp:\/\/ritmo.ir:8080\/saod","album_info":{"album_name":"\u0632\u0646\u062f\u06af\u06cc \u062f\u0648\u06af\u0627\u0646\u0647 \u0648\u0631\u0648\u0646\u06cc\u06a9","album_id":760},"publish_time":{"year":null,"month":null},"rbt_code":"","description":"","rtsp_path":"rtsp:\/\/ritmo.ir:8080\/saod\/_definst_\/mp4:ritmo\/128\/sample_44100_2_6acb084470c0a8bdf431d5427d1f29bc.m4a","hls_path":"http:\/\/ritmo.ir:8080\/saod\/_definst_\/mp4:ritmo\/128\/sample_44100_2_6acb084470c0a8bdf431d5427d1f29bc.m4a\/playlist.m3u8","file_duration":6,"price":500.0,"free_from":0,"file_checksum":"ba43c6a59d0769df85c317981360694f","name_en":"Veronique","image_path_absolute":"http:\/\/api.ritmo.media\/media\/album\/images\/2ca65f58e35d9ad45bf7f3ae5cfd08f1.jpg","file_duration_real":34,"track_number":6,"artists_info":[{"name_fa":"\u0632\u0628\u06cc\u06af\u0646\u0641 \u067e\u0631\u0627\u06cc\u0632\u0646\u0631","name_en":"Zbigniew preisner","type":"singer","id":540}],"free_to_listen":false,"user_activity":null}