{"is_sample_playing":true,"download_path":"http:\/\/api.ritmo.media\/api\/tracks\/9879\/download","free_to":0,"name_fa":"\u0646\u0648\u062d\u0647 \u06cc \u0639\u0632\u0627\u062f\u0627\u0631\u06cc \u0645\u0631\u062f\u0627\u0646\u0647 8","like_count":0,"lyric":"","thumbnail_list":{"x_200":{"image_path_absolute":"http:\/\/api.ritmo.media\/media\/cache\/fc\/1b\/fc1bae23605e35021f5cfa570076131c.jpg","size":[200,200]},"x_500":{"image_path_absolute":"http:\/\/api.ritmo.media\/media\/cache\/d7\/c2\/d7c26cbdbe9c3bf0b2bbad6dd31672c0.jpg","size":[500,500]}},"id":9879,"file_duration_formatted":"50''","rtmp_path":"mp4:ritmo\/128\/sample_44100_2_ec73a08511f0f15158c830720aee7588.m4a","free_to_download":false,"dislike_count":0,"file_size_MB":9.73,"rtmp_base":"rtmp:\/\/ritmo.ir:8080\/saod","album_info":{"album_name":"\u0627\u0647\u0644 \u0645\u0627\u062a\u06452","album_id":839},"publish_time":{"year":null,"month":null},"rbt_code":"","description":"","rtsp_path":"rtsp:\/\/ritmo.ir:8080\/saod\/_definst_\/mp4:ritmo\/128\/sample_44100_2_ec73a08511f0f15158c830720aee7588.m4a","hls_path":"http:\/\/ritmo.ir:8080\/saod\/_definst_\/mp4:ritmo\/128\/sample_44100_2_ec73a08511f0f15158c830720aee7588.m4a\/playlist.m3u8","file_duration":50,"price":500.0,"free_from":0,"file_checksum":"53ce272583440db0c152007c07d542d4","name_en":"Nowhe of Men's Mourning 8","image_path_absolute":"http:\/\/api.ritmo.media\/media\/album\/images\/8f7d807e1f53eff5f9efbe5cb81090fb.jpg","file_duration_real":254,"track_number":4,"artists_info":[{"name_fa":"\u0645\u062d\u0633\u0646 \u0634\u0631\u06cc\u0641\u06cc\u0627\u0646","name_en":"mohsen sharifian","type":"singer","id":426}],"free_to_listen":false,"user_activity":null}